voluptuous-stubs/__init__.pyi
voluptuous-stubs/error.pyi
voluptuous-stubs/humanize.pyi
voluptuous-stubs/schema_builder.pyi
voluptuous-stubs/util.pyi
voluptuous-stubs/validators.pyi
voluptuous_stubs-0.1.1.dist-info/METADATA
voluptuous_stubs-0.1.1.dist-info/WHEEL
voluptuous_stubs-0.1.1.dist-info/top_level.txt
voluptuous_stubs-0.1.1.dist-info/RECORD
