Metadata-Version: 2.1
Name: voluptuous-stubs
Version: 0.1.1
Summary: voluptuous stubs
Home-page: https://github.com/ryanwang520/voluptuous-stubs
Author: Ryan Wang
Author-email: hwwangwang@gmail.com
License: MIT License
Platform: UNKNOWN
Classifier: Development Status :: 3 - Alpha
Classifier: Programming Language :: Python :: 3
Requires-Dist: mypy (>=0.720)
Requires-Dist: typing-extensions (>=3.7.4)
